{
  "place_id": "0x80c2c7cb50cbde27:0x657b5b84be1a31ec",
  "venue_name": "BROKEN MOUTH | Lee's Homestyle",
  "chips": [
    {
      "label": "spam musubi",
      "mention_count": 96
    },
    {
      "label": "purple rice",
      "mention_count": 69
    },
    {
      "label": "hawaiian food",
      "mention_count": 63
    },
    {
      "label": "garlic shrimp",
      "mention_count": 38
    },
    {
      "label": "cucumber kimchi",
      "mention_count": 31
    },
    {
      "label": "beef plate",
      "mention_count": 49
    },
    {
      "label": "mac salad",
      "mention_count": 38
    },
    {
      "label": "meat jun",
      "mention_count": 17
    },
    {
      "label": "furikake",
      "mention_count": 15
    },
    {
      "label": "potato mac salad",
      "mention_count": 7
    }
  ],
  "scraped_at": "2026-05-16T05:20:53Z",
  "city": "Los Angeles",
  "key": "broken-mouth-lees-homestyle-los-angele"
}