{
  "place_id": "0x80c2dba4bc029da7:0x9509d583d37e5ed6",
  "venue_name": "Dumpling House",
  "chips": [
    {
      "label": "soup dumplings",
      "mention_count": 23
    },
    {
      "label": "beef noodle soup",
      "mention_count": 12
    },
    {
      "label": "Green Onion Pancake",
      "mention_count": 16
    },
    {
      "label": "chili oil",
      "mention_count": 7
    },
    {
      "label": "juicy pork dumplings",
      "mention_count": 4
    },
    {
      "label": "lamb dumplings",
      "mention_count": 3
    },
    {
      "label": "eggplant with garlic sauce",
      "mention_count": 3
    },
    {
      "label": "dumpling skin",
      "mention_count": 3
    },
    {
      "label": "pork wontons in spicy sauce",
      "mention_count": 2
    },
    {
      "label": "spicy food",
      "mention_count": 23
    }
  ],
  "scraped_at": "2026-05-16T05:12:24Z",
  "city": "Arcadia",
  "key": "magic-dumplings-arcadia"
}