{
  "place_id": "0x89c259a8f9c85799:0xa94402a5a1f4db65",
  "venue_name": "Gammeeok",
  "chips": [
    {
      "label": "seolleongtang",
      "mention_count": 144
    },
    {
      "label": "kkakdugi",
      "mention_count": 27
    },
    {
      "label": "soondae",
      "mention_count": 17
    },
    {
      "label": "galbitang",
      "mention_count": 13
    },
    {
      "label": "kimchi jigae",
      "mention_count": 11
    },
    {
      "label": "jokbal",
      "mention_count": 11
    },
    {
      "label": "ox bone soup",
      "mention_count": 10
    },
    {
      "label": "seafood pancake",
      "mention_count": 16
    },
    {
      "label": "yukgaejang",
      "mention_count": 11
    },
    {
      "label": "doganitang",
      "mention_count": 6
    }
  ],
  "scraped_at": "2026-05-16T05:10:39Z",
  "city": "Koreatown",
  "key": "gammeeok-koreatown"
}